rpunct/__init__.py
rpunct/punctuate.py
rpunct/utils.py
rpunct-1.0.2.dist-info/METADATA
rpunct-1.0.2.dist-info/WHEEL
rpunct-1.0.2.dist-info/top_level.txt
rpunct-1.0.2.dist-info/RECORD
