Metadata-Version: 2.1
Name: rpunct
Version: 1.0.2
Summary: An easy-to-use package to  restore punctuation of text.
Home-page: https://github.com/Felflare/rpunct
Author: Daulet Nurmanbetov
Author-email: daulet.nurmanbetov@gmail.com
License: UNKNOWN
Platform: UNKNOWN
Classifier: Intended Audience :: Science/Research
Classifier: License :: OSI Approved :: MIT License
Classifier: Programming Language :: Python :: 3
Classifier: Topic :: Scientific/Engineering :: Artificial Intelligence
Requires-Python: >=3.6
Requires-Dist: langdetect (==1.0.9)
Requires-Dist: pandas (==1.2.4)
Requires-Dist: simpletransformers (==0.61.4)
Requires-Dist: six (==1.16.0)
Requires-Dist: torch (==1.8.1)
